LICENSE
MANIFEST.in
README.rst
setup.py
django_rte.egg-info/PKG-INFO
django_rte.egg-info/SOURCES.txt
django_rte.egg-info/dependency_links.txt
django_rte.egg-info/not-zip-safe
django_rte.egg-info/top_level.txt
rte/__init__.py
rte/fields.py
rte/widgets.py
rte/static/rte/.tiny.config.js.swp
rte/static/rte/tiny.config.js
rte/static/rte/tiny_mce/jquery.tinymce.js
rte/static/rte/tiny_mce/license.txt
rte/static/rte/tiny_mce/tiny_mce.js
rte/static/rte/tiny_mce/tiny_mce_popup.js
rte/static/rte/tiny_mce/tiny_mce_src.js
rte/static/rte/tiny_mce/langs/ar.js
rte/static/rte/tiny_mce/langs/az.js
rte/static/rte/tiny_mce/langs/be.js
rte/static/rte/tiny_mce/langs/bg.js
rte/static/rte/tiny_mce/langs/bn.js
rte/static/rte/tiny_mce/langs/br.js
rte/static/rte/tiny_mce/langs/bs.js
rte/static/rte/tiny_mce/langs/ca.js
rte/static/rte/tiny_mce/langs/ch.js
rte/static/rte/tiny_mce/langs/cn.js
rte/static/rte/tiny_mce/langs/cs.js
rte/static/rte/tiny_mce/langs/cy.js
rte/static/rte/tiny_mce/langs/da.js
rte/static/rte/tiny_mce/langs/de.js
rte/static/rte/tiny_mce/langs/dv.js
rte/static/rte/tiny_mce/langs/el.js
rte/static/rte/tiny_mce/langs/en.js
rte/static/rte/tiny_mce/langs/eo.js
rte/static/rte/tiny_mce/langs/es.js
rte/static/rte/tiny_mce/langs/et.js
rte/static/rte/tiny_mce/langs/eu.js
rte/static/rte/tiny_mce/langs/fa.js
rte/static/rte/tiny_mce/langs/fi.js
rte/static/rte/tiny_mce/langs/fr.js
rte/static/rte/tiny_mce/langs/gl.js
rte/static/rte/tiny_mce/langs/gu.js
rte/static/rte/tiny_mce/langs/he.js
rte/static/rte/tiny_mce/langs/hi.js
rte/static/rte/tiny_mce/langs/hr.js
rte/static/rte/tiny_mce/langs/hu.js
rte/static/rte/tiny_mce/langs/hy.js
rte/static/rte/tiny_mce/langs/ia.js
rte/static/rte/tiny_mce/langs/id.js
rte/static/rte/tiny_mce/langs/is.js
rte/static/rte/tiny_mce/langs/it.js
rte/static/rte/tiny_mce/langs/ja.js
rte/static/rte/tiny_mce/langs/ka.js
rte/static/rte/tiny_mce/langs/kl.js
rte/static/rte/tiny_mce/langs/km.js
rte/static/rte/tiny_mce/langs/ko.js
rte/static/rte/tiny_mce/langs/lb.js
rte/static/rte/tiny_mce/langs/lt.js
rte/static/rte/tiny_mce/langs/lv.js
rte/static/rte/tiny_mce/langs/mk.js
rte/static/rte/tiny_mce/langs/ml.js
